[
  {
    "id": 0,
    "name": "Praitun Yoovidhya",
    "picture": "images/B1.jpg",
    "return": "3%",
    "idtree": "T001",
    "loan": 3000
  },
  {
    "id": 1,
    "name": "Ti Nung Cha Narkbunnum",
    "picture": "images/B2.jpg",
    "return": "4%",
    "idtree": "T002",
    "loan": 3500
  },
  {
    "id": 2,
    "name": "Choonhavan Atitarn",
    "picture": "images/B3.jpg",
    "return": "5%",
    "idtree": "T003",
    "loan": 4500
  },
  {
    "id": 3,
    "name": "Adirake Kaewburesai",
    "picture": "images/B4.jpg",
    "return": "4.5%",
    "idtree": "T004",
    "loan": 5000
  },
  {
    "id": 4,
    "name": "Sunisa Yuvaves",
    "picture": "images/B5.jpg",
    "return": "2.5%",
    "idtree": "T005",
    "loan": 4000
  },
  {
    "id": 5,
    "name": "Kamala Chan'ocha",
    "picture": "images/B6.jpg",
    "return": "4.5%",
    "idtree": "T006",
    "loan": 7000
  },
  {
    "id": 6,
    "name": "Rochana Sirisopa",
    "picture": "images/B7.jpg",
    "return": "3.6%",
    "idtree": "T007",
    "loan": 7500
  },
  {
    "id": 7,
    "name": "Sangwan Sutabuhr",
    "picture": "images/B8.jpg",
    "return": "5%",
    "idtree": "T008",
    "loan": 8000
  },
  {
    "id": 8,
    "name": "Chomkwan Vejjajiva",
    "picture": "images/B9.jpg",
    "return": "3%",
    "idtree": "T009",
    "loan": 7500
  },
  {
    "id": 9,
    "name": "Thanaboon Khadpo",
    "picture": "images/B10.jpg",
    "return": "2.5",
    "idtree": "T010",
    "loan": 3000
  },
  {
    "id": 10,
    "name": "Pongkun Suppamongkon",
    "picture": "images/B11.jpg",
    "return": "2.2%",
    "idtree": "T011",
    "loan": 4000
  },
  {
    "id": 11,
    "name": "Pranop Chatwilai",
    "picture": "images/B12.jpg",
    "return": "4%",
    "idtree": "T012",
    "loan": 5000
  },
  {
    "id": 12,
    "name": "Nuananong Boripat",
    "picture": "images/B13.jpg",
    "return": "5%",
    "idtree": "T013",
    "loan": 8000
  },
  {
    "id": 13,
    "name": "Ittiporn Kongpaisarn",
    "picture": "images/B14.jpg",
    "return": "4%",
    "idtree": "T014",
    "loan": 8500
  },
  {
    "id": 14,
    "name": "Nantin Sangwit",
    "picture": "images/B15.jpg",
    "return": "2.5%",
    "idtree": "T015",
    "loan": 9000
  },
  {
    "id": 15,
    "name": "Barinot Preecha",
    "picture": "images/B16.jpg",
    "return": "4.2%",
    "idtree": "T016",
    "loan": 6500
  }
]
